async_llm_handler/__init__.py
async_llm_handler/config.py
async_llm_handler/exceptions.py
async_llm_handler/handler.py
async_llm_handler/repo_context_extractor.py
async_llm_handler/examples/async_example.py
async_llm_handler/tests/__init__.py
async_llm_handler/tests/test_handler.py
async_llm_handler/tests/test_utils.py
async_llm_handler/utils/__init__.py
async_llm_handler/utils/logger.py
async_llm_handler/utils/rate_limiter.py
async_llm_handler/utils/token_utils.py
async_llm_handler-0.2.0.dist-info/METADATA
async_llm_handler-0.2.0.dist-info/WHEEL
async_llm_handler-0.2.0.dist-info/RECORD
