Metadata-Version: 2.3
Name: async_llm_handler
Version: 0.2.0
Summary: An asynchronous handler for multiple LLM APIs
Project-URL: Homepage, https://github.com/BryanNsoh/async_llm_handler
Author-email: Bryan Nsoh <bryan.anye.5@gmail.com>
License-Expression: MIT
Keywords: api,async,llm,nlp
Requires-Python: >=3.7
Requires-Dist: aiohttp
Requires-Dist: anthropic
Requires-Dist: asyncio
Requires-Dist: google-generativeai
Requires-Dist: openai
Requires-Dist: python-dotenv
Requires-Dist: tiktoken
Provides-Extra: dev
Requires-Dist: pytest; extra == 'dev'
Requires-Dist: pytest-asyncio; extra == 'dev'
